{"latestHistoryPublishedAt":1432263108171,"publishedUrls":{"http://127.0.0.1:4000/CuratedHistory/":1431837031504,"https://github.com/basecamp/pow/issues/471":1431837031504,"https://developer.chrome.com/extensions/history":1431837031504,"http://stackoverflow.com/questions/11431337/sending-message-to-chrome-extension-from-a-web-page":1431837031504,"http://aroc.github.io/side-comments-demo/":1431837031504,"http://extensionizr.com/!#{\"modules\":[\"hidden-mode\",\"with-js-bg\",\"no-options\",\"no-override\"],\"boolean_perms\":[\"history\"],\"match_ptrns\":[\"http://www.Douglas-meyer.name/*\",\"http://localhost:4000/*\"]}":1431837031504,"http://feedly.com/i/latest":1431837031504,"http://resumeplaylist.com/?list=PLBDA2E52FB1EF80C9":1431837031504,"https://ruby5.codeschool.com/":1431837031504,"https://twitter.com/DouglasMeyer":1431837031504,"http://agar.io/":1431837031504,"file:///Users/douglas/Code/Personal/CuratedHistory/_tests/SpecRunner.html?":1431837031504,"http://devchat.tv/ruby-rogues/205-rr-eight-years-of-ruby-and-rails-with-piotr-solnica":1431837031504,"https://www.youtube.com/watch?v=IApUK_eu3Ek&list=PL86A343AB05761B48":1431837031504,"http://www.ssa.gov/cgi-bin/popularnames.cgi":1431837031504,"https://www.youtube.com/watch?v=NeUP9uMoW4Q":1431837031504,"https://developer.mozilla.org/en-US/docs/Web/JavaScript/Reference/Global_Objects/RegExp":1431837031504,"https://developer.mozilla.org/en-US/docs/Web/JavaScript/Reference/Statements/break":1431837031504,"http://www.justinweiss.com/blog/2015/05/11/a-new-way-to-understand-your-rails-apps-performance/":1431837031504,"http://cheezburger.com/8490993408":1431837031504,"http://ezgif.com/reverse?url=https://i.chzbgr.com/maxW500/8490993408/h9F7F9733/":1431837031504,"https://play.google.com/store/apps/details?id=com.sixtostart.zombiesrun&hl=en":1431837031504,"http://hackaday.com/2015/05/14/reading-resistors-with-opencv/":1431837031504,"http://www.thenovicechefblog.com/2013/02/chocolate-peanut-butter-mug-cake/":1431837031504,"https://www.youtube.com/watch?v=1n-HMSCDYtM":1431837031504,"https://html5boilerplate.com/":1431837031504,"http://getbootstrap.com/css/":1431837031504,"https://developer.mozilla.org/en-US/docs/Web/CSS/:visited":1431837031504,"http://www.halfmarathons.net/race-calendar-illinois/":1431837031504,"https://disqus.com/":1432094702202,"https://medium.com/":1432094702202,"http://tsi.github.io/inlineDisqussions/":1432094702202,"http://taylorbarr.com/blog/how-to-install-inline-comments-or-medium-com-style-notes-to-your-blog/":1432094702202,"http://www.yuchoychicago.com/":1432094702202,"http://neovim.io/":1432094702202,"http://sporto.github.io/blog/2013/02/22/a-plain-english-guide-to-javascript-prototypes/":1432094702202,"http://jasmine.github.io/edge/introduction.html":1432094702202,"http://www.tfw2005.com/transformers-news/attach/4/0/5/9/7/Rescue-Bots_1322822023.jpg \"Transformers: Rescue Bots\"":1432263108171,"http://boingboing.net/2015/05/20/deltas-awesome-safety-video.html":1432263108171,"https://www.youtube.com/watch?v=9lCzIypqt7E":1432263108171,"https://www.youtube.com/watch?v=FlBO5LHchu0":1432263108171,"http://99percentinvisible.org/episode/the-nutshell-studies/":1432263108171,"https://github.com/philschatz/octokat.js":1432263108171,"https://github.com/DouglasMeyer/CuratedHistory":1432263108171,"http://www.amazon.com/Skullcandy-Method-Resistant-Sports-Performance/dp/B00NIGXFKK/ref=sr_1_2?ie=UTF8&qid=1432174855&sr=8-2&keywords=skullcandy+headphones+method":1432263108171,"https://twitter.com/ISS_Research":1432263108171,"http://www.thetimezoneconverter.com/":1432263108171,"http://www.bioedonline.org/library/media/photos-and-video/butterflies-in-space/flight-attempt-in-microgravity/":1432263108171,"http://clrs.cc/":1432263108171,"http://www.mikeperham.com/2015/05/08/timeout-rubys-most-dangerous-api/":1432263108171,"http://cheezburger.com/8495556864/funny-animated-gifs-when-the-catnip-hits?utm_source=feedburner&utm_medium=feed&utm_campaign=Feed%3A+SenorGif+%28Se%C3%B1or+Gif%29&utm_content=FeedBurner":1432263108171,"http://highlandjs.org/":1432263108171,"https://css-tricks.com/snippets/css/a-guide-to-flexbox/":1432263108171}}